django_facebook_capi/__init__.py
django_facebook_capi/admin.py
django_facebook_capi/capi_utils.py
django_facebook_capi/models.py
django_facebook_capi/migrations/__init__.py
django_facebook_capi-1.1.6.dist-info/licenses/LICENSE
django_facebook_capi-1.1.6.dist-info/METADATA
django_facebook_capi-1.1.6.dist-info/WHEEL
django_facebook_capi-1.1.6.dist-info/top_level.txt
django_facebook_capi-1.1.6.dist-info/RECORD
